{
  "-176,-56": {
    "SourceVersionHash": "EHFDnCqJnaJNk6rTUtHHziRemy8=",
    "VersionHash": "vola4tOPXi26vSXZqwtCboPndn4="
  },
  "-175,-56": {
    "SourceVersionHash": "EHFDnCqJnaJNk6rTUtHHziRemy8=",
    "VersionHash": "vola4tOPXi26vSXZqwtCboPndn4="
  },
  "-173,-56": {
    "SourceVersionHash": "EHFDnCqJnaJNk6rTUtHHziRemy8=",
    "VersionHash": "vola4tOPXi26vSXZqwtCboPndn4="
  },
  "-174,-56": {
    "SourceVersionHash": "EHFDnCqJnaJNk6rTUtHHziRemy8=",
    "VersionHash": "vola4tOPXi26vSXZqwtCboPndn4="
  },
  "-172,-56": {
    "SourceVersionHash": "EHFDnCqJnaJNk6rTUtHHziRemy8=",
    "VersionHash": "vola4tOPXi26vSXZqwtCboPndn4="
  },
  "-171,-56": {
    "SourceVersionHash": "EHFDnCqJnaJNk6rTUtHHziRemy8=",
    "VersionHash": "vola4tOPXi26vSXZqwtCboPndn4="
  },
  "-176,-55": {
    "SourceVersionHash": "EHFDnCqJnaJNk6rTUtHHziRemy8=",
    "VersionHash": "oaqSyyDCWN9Fk/tR+1yF+SFZiOc="
  },
  "-175,-55": {
    "SourceVersionHash": "EHFDnCqJnaJNk6rTUtHHziRemy8=",
    "VersionHash": "oaqSyyDCWN9Fk/tR+1yF+SFZiOc="
  },
  "-174,-55": {
    "SourceVersionHash": "EHFDnCqJnaJNk6rTUtHHziRemy8=",
    "VersionHash": "oaqSyyDCWN9Fk/tR+1yF+SFZiOc="
  },
  "-173,-55": {
    "SourceVersionHash": "EHFDnCqJnaJNk6rTUtHHziRemy8=",
    "VersionHash": "oaqSyyDCWN9Fk/tR+1yF+SFZiOc="
  },
  "-172,-55": {
    "SourceVersionHash": "EHFDnCqJnaJNk6rTUtHHziRemy8=",
    "VersionHash": "oaqSyyDCWN9Fk/tR+1yF+SFZiOc="
  },
  "-176,-54": {
    "SourceVersionHash": "EHFDnCqJnaJNk6rTUtHHziRemy8=",
    "VersionHash": "oaqSyyDCWN9Fk/tR+1yF+SFZiOc="
  },
  "-171,-55": {
    "SourceVersionHash": "EHFDnCqJnaJNk6rTUtHHziRemy8=",
    "VersionHash": "oaqSyyDCWN9Fk/tR+1yF+SFZiOc="
  },
  "-175,-54": {
    "SourceVersionHash": "EHFDnCqJnaJNk6rTUtHHziRemy8=",
    "VersionHash": "oaqSyyDCWN9Fk/tR+1yF+SFZiOc="
  },
  "-173,-54": {
    "SourceVersionHash": "EHFDnCqJnaJNk6rTUtHHziRemy8=",
    "VersionHash": "oaqSyyDCWN9Fk/tR+1yF+SFZiOc="
  },
  "-174,-54": {
    "SourceVersionHash": "EHFDnCqJnaJNk6rTUtHHziRemy8=",
    "VersionHash": "oaqSyyDCWN9Fk/tR+1yF+SFZiOc="
  },
  "-172,-54": {
    "SourceVersionHash": "EHFDnCqJnaJNk6rTUtHHziRemy8=",
    "VersionHash": "dV5uXza9O/MAdf/s7uTLfPzE/aU="
  },
  "-171,-54": {
    "SourceVersionHash": "EHFDnCqJnaJNk6rTUtHHziRemy8=",
    "VersionHash": "dV5uXza9O/MAdf/s7uTLfPzE/aU="
  },
  "-176,-53": {
    "SourceVersionHash": "EHFDnCqJnaJNk6rTUtHHziRemy8=",
    "VersionHash": "dV5uXza9O/MAdf/s7uTLfPzE/aU="
  },
  "-174,-53": {
    "SourceVersionHash": "EHFDnCqJnaJNk6rTUtHHziRemy8=",
    "VersionHash": "dV5uXza9O/MAdf/s7uTLfPzE/aU="
  },
  "-173,-53": {
    "SourceVersionHash": "EHFDnCqJnaJNk6rTUtHHziRemy8=",
    "VersionHash": "F6Djb+GXU8dxJOFQqeYAvdgdoLk="
  },
  "-172,-53": {
    "SourceVersionHash": "EHFDnCqJnaJNk6rTUtHHziRemy8=",
    "VersionHash": "F6Djb+GXU8dxJOFQqeYAvdgdoLk="
  },
  "-171,-53": {
    "SourceVersionHash": "EHFDnCqJnaJNk6rTUtHHziRemy8=",
    "VersionHash": "F6Djb+GXU8dxJOFQqeYAvdgdoLk="
  },
  "-175,-53": {
    "SourceVersionHash": "EHFDnCqJnaJNk6rTUtHHziRemy8=",
    "VersionHash": "F6Djb+GXU8dxJOFQqeYAvdgdoLk="
  },
  "-174,-52": {
    "SourceVersionHash": "EHFDnCqJnaJNk6rTUtHHziRemy8=",
    "VersionHash": "F6Djb+GXU8dxJOFQqeYAvdgdoLk="
  },
  "-175,-52": {
    "SourceVersionHash": "EHFDnCqJnaJNk6rTUtHHziRemy8=",
    "VersionHash": "F6Djb+GXU8dxJOFQqeYAvdgdoLk="
  },
  "-173,-52": {
    "SourceVersionHash": "EHFDnCqJnaJNk6rTUtHHziRemy8=",
    "VersionHash": "F6Djb+GXU8dxJOFQqeYAvdgdoLk="
  },
  "-176,-52": {
    "SourceVersionHash": "EHFDnCqJnaJNk6rTUtHHziRemy8=",
    "VersionHash": "F6Djb+GXU8dxJOFQqeYAvdgdoLk="
  },
  "-171,-52": {
    "SourceVersionHash": "EHFDnCqJnaJNk6rTUtHHziRemy8=",
    "VersionHash": "F6Djb+GXU8dxJOFQqeYAvdgdoLk="
  },
  "-172,-52": {
    "SourceVersionHash": "EHFDnCqJnaJNk6rTUtHHziRemy8=",
    "VersionHash": "ja72DUe5z5Ryj2UGahr23XE+u24="
  },
  "-176,-51": {
    "SourceVersionHash": "EHFDnCqJnaJNk6rTUtHHziRemy8=",
    "VersionHash": "aVilhXYnNwUgkkUm8vwD3rdGLKM="
  },
  "-175,-51": {
    "SourceVersionHash": "EHFDnCqJnaJNk6rTUtHHziRemy8=",
    "VersionHash": "0V8mlWQQj0Rj+UjxI27ynA1DxKs="
  },
  "-173,-51": {
    "SourceVersionHash": "EHFDnCqJnaJNk6rTUtHHziRemy8=",
    "VersionHash": "0V8mlWQQj0Rj+UjxI27ynA1DxKs="
  },
  "-174,-51": {
    "SourceVersionHash": "EHFDnCqJnaJNk6rTUtHHziRemy8=",
    "VersionHash": "mJ/vsUr1QpH5qC760P2vtuO9sao="
  },
  "-172,-51": {
    "SourceVersionHash": "EHFDnCqJnaJNk6rTUtHHziRemy8=",
    "VersionHash": "sThpznseFSPYmOc8X7DpLHW3z74="
  },
  "-171,-51": {
    "SourceVersionHash": "EHFDnCqJnaJNk6rTUtHHziRemy8=",
    "VersionHash": "sThpznseFSPYmOc8X7DpLHW3z74="
  }
}