{
  "-112,-46": {
    "SourceVersionHash": "IA7xe72j9wVck8NSOsOnHq0bmM8=",
    "VersionHash": "+NHlG1s4mxblaPIgljkEr5tr+hA="
  },
  "-111,-47": {
    "SourceVersionHash": "IA7xe72j9wVck8NSOsOnHq0bmM8=",
    "VersionHash": "+NHlG1s4mxblaPIgljkEr5tr+hA="
  },
  "-111,-43": {
    "SourceVersionHash": "IA7xe72j9wVck8NSOsOnHq0bmM8=",
    "VersionHash": "+NHlG1s4mxblaPIgljkEr5tr+hA="
  },
  "-112,-47": {
    "SourceVersionHash": "IA7xe72j9wVck8NSOsOnHq0bmM8=",
    "VersionHash": "+NHlG1s4mxblaPIgljkEr5tr+hA="
  },
  "-113,-46": {
    "SourceVersionHash": "sl3YK3gvxD2VSxs5z+sBMcJ9PiI=",
    "VersionHash": "+NHlG1s4mxblaPIgljkEr5tr+hA="
  },
  "-111,-46": {
    "SourceVersionHash": "IA7xe72j9wVck8NSOsOnHq0bmM8=",
    "VersionHash": "+NHlG1s4mxblaPIgljkEr5tr+hA="
  },
  "-111,-42": {
    "SourceVersionHash": "IA7xe72j9wVck8NSOsOnHq0bmM8=",
    "VersionHash": "+NHlG1s4mxblaPIgljkEr5tr+hA="
  },
  "-112,-45": {
    "SourceVersionHash": "IA7xe72j9wVck8NSOsOnHq0bmM8=",
    "VersionHash": "+NHlG1s4mxblaPIgljkEr5tr+hA="
  },
  "-111,-44": {
    "SourceVersionHash": "IA7xe72j9wVck8NSOsOnHq0bmM8=",
    "VersionHash": "+NHlG1s4mxblaPIgljkEr5tr+hA="
  },
  "-111,-45": {
    "SourceVersionHash": "IA7xe72j9wVck8NSOsOnHq0bmM8=",
    "VersionHash": "+NHlG1s4mxblaPIgljkEr5tr+hA="
  },
  "-113,-47": {
    "SourceVersionHash": "sl3YK3gvxD2VSxs5z+sBMcJ9PiI=",
    "VersionHash": "+NHlG1s4mxblaPIgljkEr5tr+hA="
  },
  "-113,-45": {
    "SourceVersionHash": "sl3YK3gvxD2VSxs5z+sBMcJ9PiI=",
    "VersionHash": "+NHlG1s4mxblaPIgljkEr5tr+hA="
  },
  "-113,-44": {
    "SourceVersionHash": "sl3YK3gvxD2VSxs5z+sBMcJ9PiI=",
    "VersionHash": "+NHlG1s4mxblaPIgljkEr5tr+hA="
  },
  "-112,-44": {
    "SourceVersionHash": "IA7xe72j9wVck8NSOsOnHq0bmM8=",
    "VersionHash": "+NHlG1s4mxblaPIgljkEr5tr+hA="
  },
  "-113,-42": {
    "SourceVersionHash": "sl3YK3gvxD2VSxs5z+sBMcJ9PiI=",
    "VersionHash": "+NHlG1s4mxblaPIgljkEr5tr+hA="
  },
  "-113,-43": {
    "SourceVersionHash": "sl3YK3gvxD2VSxs5z+sBMcJ9PiI=",
    "VersionHash": "+NHlG1s4mxblaPIgljkEr5tr+hA="
  },
  "-112,-43": {
    "SourceVersionHash": "IA7xe72j9wVck8NSOsOnHq0bmM8=",
    "VersionHash": "+NHlG1s4mxblaPIgljkEr5tr+hA="
  },
  "-112,-42": {
    "SourceVersionHash": "IA7xe72j9wVck8NSOsOnHq0bmM8=",
    "VersionHash": "+NHlG1s4mxblaPIgljkEr5tr+hA="
  },
  "-111,-41": {
    "SourceVersionHash": "IA7xe72j9wVck8NSOsOnHq0bmM8=",
    "VersionHash": "AD6Pq6bzxKUIAM0NZPNFXJ7kejg="
  },
  "-111,-49": {
    "SourceVersionHash": "pKj2H69vL3o4uHJ4omCd2arg/HE=",
    "VersionHash": "AD6Pq6bzxKUIAM0NZPNFXJ7kejg="
  },
  "-111,-48": {
    "SourceVersionHash": "IA7xe72j9wVck8NSOsOnHq0bmM8=",
    "VersionHash": "AD6Pq6bzxKUIAM0NZPNFXJ7kejg="
  },
  "-113,-41": {
    "SourceVersionHash": "sl3YK3gvxD2VSxs5z+sBMcJ9PiI=",
    "VersionHash": "AD6Pq6bzxKUIAM0NZPNFXJ7kejg="
  },
  "-112,-41": {
    "SourceVersionHash": "IA7xe72j9wVck8NSOsOnHq0bmM8=",
    "VersionHash": "AD6Pq6bzxKUIAM0NZPNFXJ7kejg="
  },
  "-113,-49": {
    "SourceVersionHash": "Sv2q7txlE9ncuwf11F+1P76cczY=",
    "VersionHash": "AD6Pq6bzxKUIAM0NZPNFXJ7kejg="
  },
  "-112,-49": {
    "SourceVersionHash": "pKj2H69vL3o4uHJ4omCd2arg/HE=",
    "VersionHash": "AD6Pq6bzxKUIAM0NZPNFXJ7kejg="
  },
  "-113,-48": {
    "SourceVersionHash": "sl3YK3gvxD2VSxs5z+sBMcJ9PiI=",
    "VersionHash": "AD6Pq6bzxKUIAM0NZPNFXJ7kejg="
  },
  "-112,-48": {
    "SourceVersionHash": "IA7xe72j9wVck8NSOsOnHq0bmM8=",
    "VersionHash": "AD6Pq6bzxKUIAM0NZPNFXJ7kejg="
  },
  "-120,-50": {
    "SourceVersionHash": "Sv2q7txlE9ncuwf11F+1P76cczY=",
    "VersionHash": "OsdKsYE9bLspOsbeCXFhOXa5QQs="
  },
  "-120,-49": {
    "SourceVersionHash": "Sv2q7txlE9ncuwf11F+1P76cczY=",
    "VersionHash": "OsdKsYE9bLspOsbeCXFhOXa5QQs="
  },
  "-120,-48": {
    "SourceVersionHash": "sl3YK3gvxD2VSxs5z+sBMcJ9PiI=",
    "VersionHash": "OsdKsYE9bLspOsbeCXFhOXa5QQs="
  },
  "-119,-50": {
    "SourceVersionHash": "Sv2q7txlE9ncuwf11F+1P76cczY=",
    "VersionHash": "p0zdY60tJjNs91NQkGFqyEIDhl8="
  },
  "-115,-50": {
    "SourceVersionHash": "Sv2q7txlE9ncuwf11F+1P76cczY=",
    "VersionHash": "p0zdY60tJjNs91NQkGFqyEIDhl8="
  },
  "-116,-50": {
    "SourceVersionHash": "Sv2q7txlE9ncuwf11F+1P76cczY=",
    "VersionHash": "p0zdY60tJjNs91NQkGFqyEIDhl8="
  },
  "-118,-50": {
    "SourceVersionHash": "Sv2q7txlE9ncuwf11F+1P76cczY=",
    "VersionHash": "p0zdY60tJjNs91NQkGFqyEIDhl8="
  },
  "-114,-50": {
    "SourceVersionHash": "Sv2q7txlE9ncuwf11F+1P76cczY=",
    "VersionHash": "p0zdY60tJjNs91NQkGFqyEIDhl8="
  },
  "-117,-50": {
    "SourceVersionHash": "Sv2q7txlE9ncuwf11F+1P76cczY=",
    "VersionHash": "p0zdY60tJjNs91NQkGFqyEIDhl8="
  },
  "-119,-49": {
    "SourceVersionHash": "Sv2q7txlE9ncuwf11F+1P76cczY=",
    "VersionHash": "p0zdY60tJjNs91NQkGFqyEIDhl8="
  },
  "-118,-49": {
    "SourceVersionHash": "Sv2q7txlE9ncuwf11F+1P76cczY=",
    "VersionHash": "p0zdY60tJjNs91NQkGFqyEIDhl8="
  },
  "-117,-49": {
    "SourceVersionHash": "Sv2q7txlE9ncuwf11F+1P76cczY=",
    "VersionHash": "p0zdY60tJjNs91NQkGFqyEIDhl8="
  },
  "-116,-49": {
    "SourceVersionHash": "Sv2q7txlE9ncuwf11F+1P76cczY=",
    "VersionHash": "p0zdY60tJjNs91NQkGFqyEIDhl8="
  },
  "-119,-48": {
    "SourceVersionHash": "sl3YK3gvxD2VSxs5z+sBMcJ9PiI=",
    "VersionHash": "p0zdY60tJjNs91NQkGFqyEIDhl8="
  },
  "-114,-49": {
    "SourceVersionHash": "Sv2q7txlE9ncuwf11F+1P76cczY=",
    "VersionHash": "p0zdY60tJjNs91NQkGFqyEIDhl8="
  },
  "-117,-48": {
    "SourceVersionHash": "sl3YK3gvxD2VSxs5z+sBMcJ9PiI=",
    "VersionHash": "p0zdY60tJjNs91NQkGFqyEIDhl8="
  },
  "-115,-49": {
    "SourceVersionHash": "Sv2q7txlE9ncuwf11F+1P76cczY=",
    "VersionHash": "p0zdY60tJjNs91NQkGFqyEIDhl8="
  },
  "-116,-48": {
    "SourceVersionHash": "sl3YK3gvxD2VSxs5z+sBMcJ9PiI=",
    "VersionHash": "p0zdY60tJjNs91NQkGFqyEIDhl8="
  },
  "-115,-48": {
    "SourceVersionHash": "sl3YK3gvxD2VSxs5z+sBMcJ9PiI=",
    "VersionHash": "p0zdY60tJjNs91NQkGFqyEIDhl8="
  },
  "-118,-48": {
    "SourceVersionHash": "sl3YK3gvxD2VSxs5z+sBMcJ9PiI=",
    "VersionHash": "p0zdY60tJjNs91NQkGFqyEIDhl8="
  },
  "-114,-48": {
    "SourceVersionHash": "sl3YK3gvxD2VSxs5z+sBMcJ9PiI=",
    "VersionHash": "p0zdY60tJjNs91NQkGFqyEIDhl8="
  },
  "-112,-50": {
    "SourceVersionHash": "pKj2H69vL3o4uHJ4omCd2arg/HE=",
    "VersionHash": "p0zdY60tJjNs91NQkGFqyEIDhl8="
  },
  "-113,-50": {
    "SourceVersionHash": "Sv2q7txlE9ncuwf11F+1P76cczY=",
    "VersionHash": "p0zdY60tJjNs91NQkGFqyEIDhl8="
  },
  "-111,-50": {
    "SourceVersionHash": "pKj2H69vL3o4uHJ4omCd2arg/HE=",
    "VersionHash": "hrKikYQdxUbXNZfhuZdI6dcn9oQ="
  },
  "-116,-41": {
    "SourceVersionHash": "sl3YK3gvxD2VSxs5z+sBMcJ9PiI=",
    "VersionHash": "5JkG/CvGuAFQOVyMU+SVwnc/yBY="
  },
  "-118,-41": {
    "SourceVersionHash": "sl3YK3gvxD2VSxs5z+sBMcJ9PiI=",
    "VersionHash": "5JkG/CvGuAFQOVyMU+SVwnc/yBY="
  },
  "-117,-41": {
    "SourceVersionHash": "sl3YK3gvxD2VSxs5z+sBMcJ9PiI=",
    "VersionHash": "5JkG/CvGuAFQOVyMU+SVwnc/yBY="
  },
  "-119,-41": {
    "SourceVersionHash": "sl3YK3gvxD2VSxs5z+sBMcJ9PiI=",
    "VersionHash": "5JkG/CvGuAFQOVyMU+SVwnc/yBY="
  },
  "-114,-41": {
    "SourceVersionHash": "sl3YK3gvxD2VSxs5z+sBMcJ9PiI=",
    "VersionHash": "5JkG/CvGuAFQOVyMU+SVwnc/yBY="
  },
  "-115,-41": {
    "SourceVersionHash": "sl3YK3gvxD2VSxs5z+sBMcJ9PiI=",
    "VersionHash": "5JkG/CvGuAFQOVyMU+SVwnc/yBY="
  },
  "-120,-41": {
    "SourceVersionHash": "sl3YK3gvxD2VSxs5z+sBMcJ9PiI=",
    "VersionHash": "5JkG/CvGuAFQOVyMU+SVwnc/yBY="
  },
  "-117,-47": {
    "SourceVersionHash": "sl3YK3gvxD2VSxs5z+sBMcJ9PiI=",
    "VersionHash": "F+DQ2qPAJSGnxvw9GxRn570agBw="
  },
  "-119,-47": {
    "SourceVersionHash": "sl3YK3gvxD2VSxs5z+sBMcJ9PiI=",
    "VersionHash": "F+DQ2qPAJSGnxvw9GxRn570agBw="
  },
  "-118,-47": {
    "SourceVersionHash": "sl3YK3gvxD2VSxs5z+sBMcJ9PiI=",
    "VersionHash": "F+DQ2qPAJSGnxvw9GxRn570agBw="
  },
  "-116,-47": {
    "SourceVersionHash": "sl3YK3gvxD2VSxs5z+sBMcJ9PiI=",
    "VersionHash": "F+DQ2qPAJSGnxvw9GxRn570agBw="
  },
  "-115,-47": {
    "SourceVersionHash": "sl3YK3gvxD2VSxs5z+sBMcJ9PiI=",
    "VersionHash": "F+DQ2qPAJSGnxvw9GxRn570agBw="
  },
  "-114,-43": {
    "SourceVersionHash": "sl3YK3gvxD2VSxs5z+sBMcJ9PiI=",
    "VersionHash": "F+DQ2qPAJSGnxvw9GxRn570agBw="
  },
  "-114,-47": {
    "SourceVersionHash": "sl3YK3gvxD2VSxs5z+sBMcJ9PiI=",
    "VersionHash": "F+DQ2qPAJSGnxvw9GxRn570agBw="
  },
  "-118,-46": {
    "SourceVersionHash": "sl3YK3gvxD2VSxs5z+sBMcJ9PiI=",
    "VersionHash": "F+DQ2qPAJSGnxvw9GxRn570agBw="
  },
  "-119,-46": {
    "SourceVersionHash": "sl3YK3gvxD2VSxs5z+sBMcJ9PiI=",
    "VersionHash": "F+DQ2qPAJSGnxvw9GxRn570agBw="
  },
  "-116,-46": {
    "SourceVersionHash": "sl3YK3gvxD2VSxs5z+sBMcJ9PiI=",
    "VersionHash": "F+DQ2qPAJSGnxvw9GxRn570agBw="
  },
  "-117,-46": {
    "SourceVersionHash": "sl3YK3gvxD2VSxs5z+sBMcJ9PiI=",
    "VersionHash": "F+DQ2qPAJSGnxvw9GxRn570agBw="
  },
  "-117,-45": {
    "SourceVersionHash": "sl3YK3gvxD2VSxs5z+sBMcJ9PiI=",
    "VersionHash": "F+DQ2qPAJSGnxvw9GxRn570agBw="
  },
  "-116,-45": {
    "SourceVersionHash": "sl3YK3gvxD2VSxs5z+sBMcJ9PiI=",
    "VersionHash": "F+DQ2qPAJSGnxvw9GxRn570agBw="
  },
  "-118,-45": {
    "SourceVersionHash": "sl3YK3gvxD2VSxs5z+sBMcJ9PiI=",
    "VersionHash": "F+DQ2qPAJSGnxvw9GxRn570agBw="
  },
  "-115,-46": {
    "SourceVersionHash": "sl3YK3gvxD2VSxs5z+sBMcJ9PiI=",
    "VersionHash": "F+DQ2qPAJSGnxvw9GxRn570agBw="
  },
  "-114,-45": {
    "SourceVersionHash": "sl3YK3gvxD2VSxs5z+sBMcJ9PiI=",
    "VersionHash": "F+DQ2qPAJSGnxvw9GxRn570agBw="
  },
  "-119,-45": {
    "SourceVersionHash": "sl3YK3gvxD2VSxs5z+sBMcJ9PiI=",
    "VersionHash": "F+DQ2qPAJSGnxvw9GxRn570agBw="
  },
  "-119,-44": {
    "SourceVersionHash": "sl3YK3gvxD2VSxs5z+sBMcJ9PiI=",
    "VersionHash": "F+DQ2qPAJSGnxvw9GxRn570agBw="
  },
  "-118,-44": {
    "SourceVersionHash": "sl3YK3gvxD2VSxs5z+sBMcJ9PiI=",
    "VersionHash": "F+DQ2qPAJSGnxvw9GxRn570agBw="
  },
  "-115,-44": {
    "SourceVersionHash": "sl3YK3gvxD2VSxs5z+sBMcJ9PiI=",
    "VersionHash": "F+DQ2qPAJSGnxvw9GxRn570agBw="
  },
  "-117,-44": {
    "SourceVersionHash": "sl3YK3gvxD2VSxs5z+sBMcJ9PiI=",
    "VersionHash": "F+DQ2qPAJSGnxvw9GxRn570agBw="
  },
  "-115,-45": {
    "SourceVersionHash": "sl3YK3gvxD2VSxs5z+sBMcJ9PiI=",
    "VersionHash": "F+DQ2qPAJSGnxvw9GxRn570agBw="
  },
  "-119,-43": {
    "SourceVersionHash": "sl3YK3gvxD2VSxs5z+sBMcJ9PiI=",
    "VersionHash": "F+DQ2qPAJSGnxvw9GxRn570agBw="
  },
  "-118,-43": {
    "SourceVersionHash": "sl3YK3gvxD2VSxs5z+sBMcJ9PiI=",
    "VersionHash": "F+DQ2qPAJSGnxvw9GxRn570agBw="
  },
  "-116,-43": {
    "SourceVersionHash": "sl3YK3gvxD2VSxs5z+sBMcJ9PiI=",
    "VersionHash": "F+DQ2qPAJSGnxvw9GxRn570agBw="
  },
  "-114,-44": {
    "SourceVersionHash": "sl3YK3gvxD2VSxs5z+sBMcJ9PiI=",
    "VersionHash": "F+DQ2qPAJSGnxvw9GxRn570agBw="
  },
  "-117,-43": {
    "SourceVersionHash": "sl3YK3gvxD2VSxs5z+sBMcJ9PiI=",
    "VersionHash": "F+DQ2qPAJSGnxvw9GxRn570agBw="
  },
  "-119,-42": {
    "SourceVersionHash": "sl3YK3gvxD2VSxs5z+sBMcJ9PiI=",
    "VersionHash": "F+DQ2qPAJSGnxvw9GxRn570agBw="
  },
  "-114,-42": {
    "SourceVersionHash": "sl3YK3gvxD2VSxs5z+sBMcJ9PiI=",
    "VersionHash": "F+DQ2qPAJSGnxvw9GxRn570agBw="
  },
  "-118,-42": {
    "SourceVersionHash": "sl3YK3gvxD2VSxs5z+sBMcJ9PiI=",
    "VersionHash": "F+DQ2qPAJSGnxvw9GxRn570agBw="
  },
  "-116,-42": {
    "SourceVersionHash": "sl3YK3gvxD2VSxs5z+sBMcJ9PiI=",
    "VersionHash": "F+DQ2qPAJSGnxvw9GxRn570agBw="
  },
  "-116,-44": {
    "SourceVersionHash": "sl3YK3gvxD2VSxs5z+sBMcJ9PiI=",
    "VersionHash": "F+DQ2qPAJSGnxvw9GxRn570agBw="
  },
  "-115,-42": {
    "SourceVersionHash": "sl3YK3gvxD2VSxs5z+sBMcJ9PiI=",
    "VersionHash": "F+DQ2qPAJSGnxvw9GxRn570agBw="
  },
  "-117,-42": {
    "SourceVersionHash": "sl3YK3gvxD2VSxs5z+sBMcJ9PiI=",
    "VersionHash": "F+DQ2qPAJSGnxvw9GxRn570agBw="
  },
  "-114,-46": {
    "SourceVersionHash": "sl3YK3gvxD2VSxs5z+sBMcJ9PiI=",
    "VersionHash": "F+DQ2qPAJSGnxvw9GxRn570agBw="
  },
  "-115,-43": {
    "SourceVersionHash": "sl3YK3gvxD2VSxs5z+sBMcJ9PiI=",
    "VersionHash": "F+DQ2qPAJSGnxvw9GxRn570agBw="
  },
  "-120,-45": {
    "SourceVersionHash": "sl3YK3gvxD2VSxs5z+sBMcJ9PiI=",
    "VersionHash": "F+DQ2qPAJSGnxvw9GxRn570agBw="
  },
  "-120,-47": {
    "SourceVersionHash": "sl3YK3gvxD2VSxs5z+sBMcJ9PiI=",
    "VersionHash": "F+DQ2qPAJSGnxvw9GxRn570agBw="
  },
  "-120,-43": {
    "SourceVersionHash": "sl3YK3gvxD2VSxs5z+sBMcJ9PiI=",
    "VersionHash": "F+DQ2qPAJSGnxvw9GxRn570agBw="
  },
  "-120,-44": {
    "SourceVersionHash": "sl3YK3gvxD2VSxs5z+sBMcJ9PiI=",
    "VersionHash": "F+DQ2qPAJSGnxvw9GxRn570agBw="
  },
  "-120,-46": {
    "SourceVersionHash": "sl3YK3gvxD2VSxs5z+sBMcJ9PiI=",
    "VersionHash": "F+DQ2qPAJSGnxvw9GxRn570agBw="
  },
  "-120,-42": {
    "SourceVersionHash": "sl3YK3gvxD2VSxs5z+sBMcJ9PiI=",
    "VersionHash": "F+DQ2qPAJSGnxvw9GxRn570agBw="
  }
}