{
  "364,139": {
    "SourceVersionHash": "bJRZqLEJJPswyF8oiSBGoRyytKk=",
    "VersionHash": "25KiH+651fzIp3Qr5AtQnoH6/2Q="
  },
  "366,139": {
    "SourceVersionHash": "bJRZqLEJJPswyF8oiSBGoRyytKk=",
    "VersionHash": "25KiH+651fzIp3Qr5AtQnoH6/2Q="
  },
  "363,138": {
    "SourceVersionHash": "bJRZqLEJJPswyF8oiSBGoRyytKk=",
    "VersionHash": "25KiH+651fzIp3Qr5AtQnoH6/2Q="
  },
  "363,139": {
    "SourceVersionHash": "bJRZqLEJJPswyF8oiSBGoRyytKk=",
    "VersionHash": "25KiH+651fzIp3Qr5AtQnoH6/2Q="
  },
  "365,139": {
    "SourceVersionHash": "bJRZqLEJJPswyF8oiSBGoRyytKk=",
    "VersionHash": "25KiH+651fzIp3Qr5AtQnoH6/2Q="
  },
  "362,138": {
    "SourceVersionHash": "bJRZqLEJJPswyF8oiSBGoRyytKk=",
    "VersionHash": "25KiH+651fzIp3Qr5AtQnoH6/2Q="
  },
  "361,139": {
    "SourceVersionHash": "bJRZqLEJJPswyF8oiSBGoRyytKk=",
    "VersionHash": "25KiH+651fzIp3Qr5AtQnoH6/2Q="
  },
  "363,137": {
    "SourceVersionHash": "bJRZqLEJJPswyF8oiSBGoRyytKk=",
    "VersionHash": "25KiH+651fzIp3Qr5AtQnoH6/2Q="
  },
  "367,139": {
    "SourceVersionHash": "bJRZqLEJJPswyF8oiSBGoRyytKk=",
    "VersionHash": "25KiH+651fzIp3Qr5AtQnoH6/2Q="
  },
  "366,137": {
    "SourceVersionHash": "bJRZqLEJJPswyF8oiSBGoRyytKk=",
    "VersionHash": "25KiH+651fzIp3Qr5AtQnoH6/2Q="
  },
  "367,137": {
    "SourceVersionHash": "bJRZqLEJJPswyF8oiSBGoRyytKk=",
    "VersionHash": "25KiH+651fzIp3Qr5AtQnoH6/2Q="
  },
  "362,137": {
    "SourceVersionHash": "bJRZqLEJJPswyF8oiSBGoRyytKk=",
    "VersionHash": "25KiH+651fzIp3Qr5AtQnoH6/2Q="
  },
  "367,138": {
    "SourceVersionHash": "bJRZqLEJJPswyF8oiSBGoRyytKk=",
    "VersionHash": "25KiH+651fzIp3Qr5AtQnoH6/2Q="
  },
  "362,139": {
    "SourceVersionHash": "bJRZqLEJJPswyF8oiSBGoRyytKk=",
    "VersionHash": "25KiH+651fzIp3Qr5AtQnoH6/2Q="
  },
  "361,137": {
    "SourceVersionHash": "bJRZqLEJJPswyF8oiSBGoRyytKk=",
    "VersionHash": "25KiH+651fzIp3Qr5AtQnoH6/2Q="
  },
  "365,137": {
    "SourceVersionHash": "bJRZqLEJJPswyF8oiSBGoRyytKk=",
    "VersionHash": "25KiH+651fzIp3Qr5AtQnoH6/2Q="
  },
  "364,138": {
    "SourceVersionHash": "bJRZqLEJJPswyF8oiSBGoRyytKk=",
    "VersionHash": "25KiH+651fzIp3Qr5AtQnoH6/2Q="
  },
  "364,137": {
    "SourceVersionHash": "bJRZqLEJJPswyF8oiSBGoRyytKk=",
    "VersionHash": "25KiH+651fzIp3Qr5AtQnoH6/2Q="
  },
  "365,138": {
    "SourceVersionHash": "bJRZqLEJJPswyF8oiSBGoRyytKk=",
    "VersionHash": "25KiH+651fzIp3Qr5AtQnoH6/2Q="
  },
  "366,138": {
    "SourceVersionHash": "bJRZqLEJJPswyF8oiSBGoRyytKk=",
    "VersionHash": "25KiH+651fzIp3Qr5AtQnoH6/2Q="
  },
  "361,138": {
    "SourceVersionHash": "bJRZqLEJJPswyF8oiSBGoRyytKk=",
    "VersionHash": "25KiH+651fzIp3Qr5AtQnoH6/2Q="
  },
  "365,136": {
    "SourceVersionHash": "bJRZqLEJJPswyF8oiSBGoRyytKk=",
    "VersionHash": "25KiH+651fzIp3Qr5AtQnoH6/2Q="
  },
  "363,136": {
    "SourceVersionHash": "bJRZqLEJJPswyF8oiSBGoRyytKk=",
    "VersionHash": "25KiH+651fzIp3Qr5AtQnoH6/2Q="
  },
  "364,136": {
    "SourceVersionHash": "bJRZqLEJJPswyF8oiSBGoRyytKk=",
    "VersionHash": "25KiH+651fzIp3Qr5AtQnoH6/2Q="
  },
  "362,136": {
    "SourceVersionHash": "bJRZqLEJJPswyF8oiSBGoRyytKk=",
    "VersionHash": "25KiH+651fzIp3Qr5AtQnoH6/2Q="
  },
  "361,136": {
    "SourceVersionHash": "bJRZqLEJJPswyF8oiSBGoRyytKk=",
    "VersionHash": "25KiH+651fzIp3Qr5AtQnoH6/2Q="
  },
  "366,136": {
    "SourceVersionHash": "bJRZqLEJJPswyF8oiSBGoRyytKk=",
    "VersionHash": "25KiH+651fzIp3Qr5AtQnoH6/2Q="
  },
  "367,136": {
    "SourceVersionHash": "bJRZqLEJJPswyF8oiSBGoRyytKk=",
    "VersionHash": "25KiH+651fzIp3Qr5AtQnoH6/2Q="
  },
  "360,139": {
    "SourceVersionHash": "bJRZqLEJJPswyF8oiSBGoRyytKk=",
    "VersionHash": "25KiH+651fzIp3Qr5AtQnoH6/2Q="
  },
  "360,137": {
    "SourceVersionHash": "bJRZqLEJJPswyF8oiSBGoRyytKk=",
    "VersionHash": "25KiH+651fzIp3Qr5AtQnoH6/2Q="
  },
  "360,136": {
    "SourceVersionHash": "bJRZqLEJJPswyF8oiSBGoRyytKk=",
    "VersionHash": "25KiH+651fzIp3Qr5AtQnoH6/2Q="
  },
  "360,138": {
    "SourceVersionHash": "bJRZqLEJJPswyF8oiSBGoRyytKk=",
    "VersionHash": "25KiH+651fzIp3Qr5AtQnoH6/2Q="
  }
}