{
  "160,159": {
    "SourceVersionHash": "ZujvpxSPBP2PkOWEsHkog7sJXTk=",
    "VersionHash": "ltGXYsHewzUkrATanNFnhDnbvfw="
  },
  "163,151": {
    "SourceVersionHash": "HuZ45HCi5kt7cRJdwxV58e39OGU=",
    "VersionHash": "k+el4a+vKt7+7kzauqTOJ91pD9Q="
  },
  "161,152": {
    "SourceVersionHash": "ZujvpxSPBP2PkOWEsHkog7sJXTk=",
    "VersionHash": "k+el4a+vKt7+7kzauqTOJ91pD9Q="
  },
  "161,151": {
    "SourceVersionHash": "HuZ45HCi5kt7cRJdwxV58e39OGU=",
    "VersionHash": "k+el4a+vKt7+7kzauqTOJ91pD9Q="
  },
  "162,150": {
    "SourceVersionHash": "HuZ45HCi5kt7cRJdwxV58e39OGU=",
    "VersionHash": "k+el4a+vKt7+7kzauqTOJ91pD9Q="
  },
  "163,150": {
    "SourceVersionHash": "HuZ45HCi5kt7cRJdwxV58e39OGU=",
    "VersionHash": "k+el4a+vKt7+7kzauqTOJ91pD9Q="
  },
  "165,150": {
    "SourceVersionHash": "HuZ45HCi5kt7cRJdwxV58e39OGU=",
    "VersionHash": "k+el4a+vKt7+7kzauqTOJ91pD9Q="
  },
  "166,150": {
    "SourceVersionHash": "HuZ45HCi5kt7cRJdwxV58e39OGU=",
    "VersionHash": "k+el4a+vKt7+7kzauqTOJ91pD9Q="
  },
  "163,152": {
    "SourceVersionHash": "ZujvpxSPBP2PkOWEsHkog7sJXTk=",
    "VersionHash": "k+el4a+vKt7+7kzauqTOJ91pD9Q="
  },
  "165,151": {
    "SourceVersionHash": "HuZ45HCi5kt7cRJdwxV58e39OGU=",
    "VersionHash": "k+el4a+vKt7+7kzauqTOJ91pD9Q="
  },
  "162,151": {
    "SourceVersionHash": "HuZ45HCi5kt7cRJdwxV58e39OGU=",
    "VersionHash": "k+el4a+vKt7+7kzauqTOJ91pD9Q="
  },
  "164,152": {
    "SourceVersionHash": "ZujvpxSPBP2PkOWEsHkog7sJXTk=",
    "VersionHash": "k+el4a+vKt7+7kzauqTOJ91pD9Q="
  },
  "162,152": {
    "SourceVersionHash": "ZujvpxSPBP2PkOWEsHkog7sJXTk=",
    "VersionHash": "k+el4a+vKt7+7kzauqTOJ91pD9Q="
  },
  "166,151": {
    "SourceVersionHash": "HuZ45HCi5kt7cRJdwxV58e39OGU=",
    "VersionHash": "k+el4a+vKt7+7kzauqTOJ91pD9Q="
  },
  "164,151": {
    "SourceVersionHash": "HuZ45HCi5kt7cRJdwxV58e39OGU=",
    "VersionHash": "k+el4a+vKt7+7kzauqTOJ91pD9Q="
  },
  "164,150": {
    "SourceVersionHash": "HuZ45HCi5kt7cRJdwxV58e39OGU=",
    "VersionHash": "k+el4a+vKt7+7kzauqTOJ91pD9Q="
  },
  "161,150": {
    "SourceVersionHash": "HuZ45HCi5kt7cRJdwxV58e39OGU=",
    "VersionHash": "k+el4a+vKt7+7kzauqTOJ91pD9Q="
  },
  "165,152": {
    "SourceVersionHash": "ZujvpxSPBP2PkOWEsHkog7sJXTk=",
    "VersionHash": "k+el4a+vKt7+7kzauqTOJ91pD9Q="
  },
  "166,152": {
    "SourceVersionHash": "ZujvpxSPBP2PkOWEsHkog7sJXTk=",
    "VersionHash": "k+el4a+vKt7+7kzauqTOJ91pD9Q="
  },
  "160,150": {
    "SourceVersionHash": "HuZ45HCi5kt7cRJdwxV58e39OGU=",
    "VersionHash": "k+el4a+vKt7+7kzauqTOJ91pD9Q="
  },
  "160,152": {
    "SourceVersionHash": "ZujvpxSPBP2PkOWEsHkog7sJXTk=",
    "VersionHash": "k+el4a+vKt7+7kzauqTOJ91pD9Q="
  },
  "160,151": {
    "SourceVersionHash": "HuZ45HCi5kt7cRJdwxV58e39OGU=",
    "VersionHash": "k+el4a+vKt7+7kzauqTOJ91pD9Q="
  },
  "167,150": {
    "SourceVersionHash": "HuZ45HCi5kt7cRJdwxV58e39OGU=",
    "VersionHash": "k+el4a+vKt7+7kzauqTOJ91pD9Q="
  },
  "168,150": {
    "SourceVersionHash": "b7yak2b7t765Rk3g6rky45z0b+c=",
    "VersionHash": "k+el4a+vKt7+7kzauqTOJ91pD9Q="
  },
  "167,151": {
    "SourceVersionHash": "HuZ45HCi5kt7cRJdwxV58e39OGU=",
    "VersionHash": "XH6Bs4RVAsZHei4ltcDPiIhONME="
  },
  "168,152": {
    "SourceVersionHash": "fNWTcGIHnnuRL9MgOyJ8nhFzlAU=",
    "VersionHash": "XH6Bs4RVAsZHei4ltcDPiIhONME="
  },
  "167,152": {
    "SourceVersionHash": "ZujvpxSPBP2PkOWEsHkog7sJXTk=",
    "VersionHash": "XH6Bs4RVAsZHei4ltcDPiIhONME="
  },
  "168,151": {
    "SourceVersionHash": "b7yak2b7t765Rk3g6rky45z0b+c=",
    "VersionHash": "XH6Bs4RVAsZHei4ltcDPiIhONME="
  },
  "160,158": {
    "SourceVersionHash": "ZujvpxSPBP2PkOWEsHkog7sJXTk=",
    "VersionHash": "md+/6Q6/WtfuOajR/gkKzyCwZek="
  },
  "160,153": {
    "SourceVersionHash": "ZujvpxSPBP2PkOWEsHkog7sJXTk=",
    "VersionHash": "md+/6Q6/WtfuOajR/gkKzyCwZek="
  },
  "160,157": {
    "SourceVersionHash": "ZujvpxSPBP2PkOWEsHkog7sJXTk=",
    "VersionHash": "md+/6Q6/WtfuOajR/gkKzyCwZek="
  },
  "160,154": {
    "SourceVersionHash": "ZujvpxSPBP2PkOWEsHkog7sJXTk=",
    "VersionHash": "md+/6Q6/WtfuOajR/gkKzyCwZek="
  },
  "160,155": {
    "SourceVersionHash": "ZujvpxSPBP2PkOWEsHkog7sJXTk=",
    "VersionHash": "md+/6Q6/WtfuOajR/gkKzyCwZek="
  },
  "160,156": {
    "SourceVersionHash": "ZujvpxSPBP2PkOWEsHkog7sJXTk=",
    "VersionHash": "md+/6Q6/WtfuOajR/gkKzyCwZek="
  },
  "166,153": {
    "SourceVersionHash": "ZujvpxSPBP2PkOWEsHkog7sJXTk=",
    "VersionHash": "iSio2Y64dLIVCj1QiUI+BE3knEQ="
  },
  "165,153": {
    "SourceVersionHash": "ZujvpxSPBP2PkOWEsHkog7sJXTk=",
    "VersionHash": "iSio2Y64dLIVCj1QiUI+BE3knEQ="
  },
  "161,153": {
    "SourceVersionHash": "ZujvpxSPBP2PkOWEsHkog7sJXTk=",
    "VersionHash": "iSio2Y64dLIVCj1QiUI+BE3knEQ="
  },
  "162,153": {
    "SourceVersionHash": "ZujvpxSPBP2PkOWEsHkog7sJXTk=",
    "VersionHash": "iSio2Y64dLIVCj1QiUI+BE3knEQ="
  },
  "166,159": {
    "SourceVersionHash": "ZujvpxSPBP2PkOWEsHkog7sJXTk=",
    "VersionHash": "iSio2Y64dLIVCj1QiUI+BE3knEQ="
  },
  "168,156": {
    "SourceVersionHash": "fNWTcGIHnnuRL9MgOyJ8nhFzlAU=",
    "VersionHash": "iSio2Y64dLIVCj1QiUI+BE3knEQ="
  },
  "167,153": {
    "SourceVersionHash": "ZujvpxSPBP2PkOWEsHkog7sJXTk=",
    "VersionHash": "iSio2Y64dLIVCj1QiUI+BE3knEQ="
  },
  "164,159": {
    "SourceVersionHash": "ZujvpxSPBP2PkOWEsHkog7sJXTk=",
    "VersionHash": "iSio2Y64dLIVCj1QiUI+BE3knEQ="
  },
  "164,158": {
    "SourceVersionHash": "ZujvpxSPBP2PkOWEsHkog7sJXTk=",
    "VersionHash": "iSio2Y64dLIVCj1QiUI+BE3knEQ="
  },
  "163,154": {
    "SourceVersionHash": "ZujvpxSPBP2PkOWEsHkog7sJXTk=",
    "VersionHash": "iSio2Y64dLIVCj1QiUI+BE3knEQ="
  },
  "167,156": {
    "SourceVersionHash": "ZujvpxSPBP2PkOWEsHkog7sJXTk=",
    "VersionHash": "iSio2Y64dLIVCj1QiUI+BE3knEQ="
  },
  "164,153": {
    "SourceVersionHash": "ZujvpxSPBP2PkOWEsHkog7sJXTk=",
    "VersionHash": "iSio2Y64dLIVCj1QiUI+BE3knEQ="
  },
  "167,155": {
    "SourceVersionHash": "ZujvpxSPBP2PkOWEsHkog7sJXTk=",
    "VersionHash": "iSio2Y64dLIVCj1QiUI+BE3knEQ="
  },
  "166,158": {
    "SourceVersionHash": "ZujvpxSPBP2PkOWEsHkog7sJXTk=",
    "VersionHash": "iSio2Y64dLIVCj1QiUI+BE3knEQ="
  },
  "162,158": {
    "SourceVersionHash": "ZujvpxSPBP2PkOWEsHkog7sJXTk=",
    "VersionHash": "iSio2Y64dLIVCj1QiUI+BE3knEQ="
  },
  "163,159": {
    "SourceVersionHash": "ZujvpxSPBP2PkOWEsHkog7sJXTk=",
    "VersionHash": "iSio2Y64dLIVCj1QiUI+BE3knEQ="
  },
  "167,157": {
    "SourceVersionHash": "ZujvpxSPBP2PkOWEsHkog7sJXTk=",
    "VersionHash": "iSio2Y64dLIVCj1QiUI+BE3knEQ="
  },
  "167,154": {
    "SourceVersionHash": "ZujvpxSPBP2PkOWEsHkog7sJXTk=",
    "VersionHash": "iSio2Y64dLIVCj1QiUI+BE3knEQ="
  },
  "161,155": {
    "SourceVersionHash": "ZujvpxSPBP2PkOWEsHkog7sJXTk=",
    "VersionHash": "iSio2Y64dLIVCj1QiUI+BE3knEQ="
  },
  "168,154": {
    "SourceVersionHash": "fNWTcGIHnnuRL9MgOyJ8nhFzlAU=",
    "VersionHash": "iSio2Y64dLIVCj1QiUI+BE3knEQ="
  },
  "161,158": {
    "SourceVersionHash": "ZujvpxSPBP2PkOWEsHkog7sJXTk=",
    "VersionHash": "iSio2Y64dLIVCj1QiUI+BE3knEQ="
  },
  "165,155": {
    "SourceVersionHash": "ZujvpxSPBP2PkOWEsHkog7sJXTk=",
    "VersionHash": "iSio2Y64dLIVCj1QiUI+BE3knEQ="
  },
  "164,154": {
    "SourceVersionHash": "ZujvpxSPBP2PkOWEsHkog7sJXTk=",
    "VersionHash": "iSio2Y64dLIVCj1QiUI+BE3knEQ="
  },
  "163,157": {
    "SourceVersionHash": "ZujvpxSPBP2PkOWEsHkog7sJXTk=",
    "VersionHash": "iSio2Y64dLIVCj1QiUI+BE3knEQ="
  },
  "163,153": {
    "SourceVersionHash": "ZujvpxSPBP2PkOWEsHkog7sJXTk=",
    "VersionHash": "iSio2Y64dLIVCj1QiUI+BE3knEQ="
  },
  "162,155": {
    "SourceVersionHash": "ZujvpxSPBP2PkOWEsHkog7sJXTk=",
    "VersionHash": "iSio2Y64dLIVCj1QiUI+BE3knEQ="
  },
  "162,154": {
    "SourceVersionHash": "ZujvpxSPBP2PkOWEsHkog7sJXTk=",
    "VersionHash": "iSio2Y64dLIVCj1QiUI+BE3knEQ="
  },
  "166,157": {
    "SourceVersionHash": "ZujvpxSPBP2PkOWEsHkog7sJXTk=",
    "VersionHash": "iSio2Y64dLIVCj1QiUI+BE3knEQ="
  },
  "165,154": {
    "SourceVersionHash": "ZujvpxSPBP2PkOWEsHkog7sJXTk=",
    "VersionHash": "iSio2Y64dLIVCj1QiUI+BE3knEQ="
  },
  "166,155": {
    "SourceVersionHash": "ZujvpxSPBP2PkOWEsHkog7sJXTk=",
    "VersionHash": "iSio2Y64dLIVCj1QiUI+BE3knEQ="
  },
  "165,156": {
    "SourceVersionHash": "ZujvpxSPBP2PkOWEsHkog7sJXTk=",
    "VersionHash": "iSio2Y64dLIVCj1QiUI+BE3knEQ="
  },
  "168,157": {
    "SourceVersionHash": "fNWTcGIHnnuRL9MgOyJ8nhFzlAU=",
    "VersionHash": "iSio2Y64dLIVCj1QiUI+BE3knEQ="
  },
  "161,156": {
    "SourceVersionHash": "ZujvpxSPBP2PkOWEsHkog7sJXTk=",
    "VersionHash": "iSio2Y64dLIVCj1QiUI+BE3knEQ="
  },
  "162,159": {
    "SourceVersionHash": "ZujvpxSPBP2PkOWEsHkog7sJXTk=",
    "VersionHash": "iSio2Y64dLIVCj1QiUI+BE3knEQ="
  },
  "161,159": {
    "SourceVersionHash": "ZujvpxSPBP2PkOWEsHkog7sJXTk=",
    "VersionHash": "iSio2Y64dLIVCj1QiUI+BE3knEQ="
  },
  "164,157": {
    "SourceVersionHash": "ZujvpxSPBP2PkOWEsHkog7sJXTk=",
    "VersionHash": "iSio2Y64dLIVCj1QiUI+BE3knEQ="
  },
  "165,159": {
    "SourceVersionHash": "ZujvpxSPBP2PkOWEsHkog7sJXTk=",
    "VersionHash": "iSio2Y64dLIVCj1QiUI+BE3knEQ="
  },
  "167,158": {
    "SourceVersionHash": "ZujvpxSPBP2PkOWEsHkog7sJXTk=",
    "VersionHash": "iSio2Y64dLIVCj1QiUI+BE3knEQ="
  },
  "163,155": {
    "SourceVersionHash": "ZujvpxSPBP2PkOWEsHkog7sJXTk=",
    "VersionHash": "iSio2Y64dLIVCj1QiUI+BE3knEQ="
  },
  "161,154": {
    "SourceVersionHash": "ZujvpxSPBP2PkOWEsHkog7sJXTk=",
    "VersionHash": "iSio2Y64dLIVCj1QiUI+BE3knEQ="
  },
  "165,158": {
    "SourceVersionHash": "ZujvpxSPBP2PkOWEsHkog7sJXTk=",
    "VersionHash": "iSio2Y64dLIVCj1QiUI+BE3knEQ="
  },
  "163,156": {
    "SourceVersionHash": "ZujvpxSPBP2PkOWEsHkog7sJXTk=",
    "VersionHash": "iSio2Y64dLIVCj1QiUI+BE3knEQ="
  },
  "164,155": {
    "SourceVersionHash": "ZujvpxSPBP2PkOWEsHkog7sJXTk=",
    "VersionHash": "iSio2Y64dLIVCj1QiUI+BE3knEQ="
  },
  "161,157": {
    "SourceVersionHash": "ZujvpxSPBP2PkOWEsHkog7sJXTk=",
    "VersionHash": "iSio2Y64dLIVCj1QiUI+BE3knEQ="
  },
  "166,156": {
    "SourceVersionHash": "ZujvpxSPBP2PkOWEsHkog7sJXTk=",
    "VersionHash": "iSio2Y64dLIVCj1QiUI+BE3knEQ="
  },
  "163,158": {
    "SourceVersionHash": "ZujvpxSPBP2PkOWEsHkog7sJXTk=",
    "VersionHash": "iSio2Y64dLIVCj1QiUI+BE3knEQ="
  },
  "165,157": {
    "SourceVersionHash": "ZujvpxSPBP2PkOWEsHkog7sJXTk=",
    "VersionHash": "iSio2Y64dLIVCj1QiUI+BE3knEQ="
  },
  "166,154": {
    "SourceVersionHash": "ZujvpxSPBP2PkOWEsHkog7sJXTk=",
    "VersionHash": "iSio2Y64dLIVCj1QiUI+BE3knEQ="
  },
  "162,157": {
    "SourceVersionHash": "ZujvpxSPBP2PkOWEsHkog7sJXTk=",
    "VersionHash": "iSio2Y64dLIVCj1QiUI+BE3knEQ="
  },
  "162,156": {
    "SourceVersionHash": "ZujvpxSPBP2PkOWEsHkog7sJXTk=",
    "VersionHash": "iSio2Y64dLIVCj1QiUI+BE3knEQ="
  },
  "168,155": {
    "SourceVersionHash": "fNWTcGIHnnuRL9MgOyJ8nhFzlAU=",
    "VersionHash": "iSio2Y64dLIVCj1QiUI+BE3knEQ="
  },
  "168,153": {
    "SourceVersionHash": "fNWTcGIHnnuRL9MgOyJ8nhFzlAU=",
    "VersionHash": "iSio2Y64dLIVCj1QiUI+BE3knEQ="
  },
  "168,158": {
    "SourceVersionHash": "fNWTcGIHnnuRL9MgOyJ8nhFzlAU=",
    "VersionHash": "iSio2Y64dLIVCj1QiUI+BE3knEQ="
  },
  "164,156": {
    "SourceVersionHash": "ZujvpxSPBP2PkOWEsHkog7sJXTk=",
    "VersionHash": "iSio2Y64dLIVCj1QiUI+BE3knEQ="
  },
  "167,159": {
    "SourceVersionHash": "ZujvpxSPBP2PkOWEsHkog7sJXTk=",
    "VersionHash": "54svRhVUKHNi/kTc1VZBsTLuaNA="
  },
  "168,159": {
    "SourceVersionHash": "fNWTcGIHnnuRL9MgOyJ8nhFzlAU=",
    "VersionHash": "54svRhVUKHNi/kTc1VZBsTLuaNA="
  },
  "169,153": {
    "SourceVersionHash": "fNWTcGIHnnuRL9MgOyJ8nhFzlAU=",
    "VersionHash": "PcVPrqSwzHIoREGCStd/Jtuwc/c="
  },
  "169,154": {
    "SourceVersionHash": "fNWTcGIHnnuRL9MgOyJ8nhFzlAU=",
    "VersionHash": "PcVPrqSwzHIoREGCStd/Jtuwc/c="
  },
  "169,151": {
    "SourceVersionHash": "b7yak2b7t765Rk3g6rky45z0b+c=",
    "VersionHash": "PcVPrqSwzHIoREGCStd/Jtuwc/c="
  },
  "169,155": {
    "SourceVersionHash": "fNWTcGIHnnuRL9MgOyJ8nhFzlAU=",
    "VersionHash": "PcVPrqSwzHIoREGCStd/Jtuwc/c="
  },
  "169,152": {
    "SourceVersionHash": "fNWTcGIHnnuRL9MgOyJ8nhFzlAU=",
    "VersionHash": "hQP3kd+OaBD0qztZYeM3xQ8YHCs="
  },
  "169,159": {
    "SourceVersionHash": "fNWTcGIHnnuRL9MgOyJ8nhFzlAU=",
    "VersionHash": "hQP3kd+OaBD0qztZYeM3xQ8YHCs="
  },
  "169,156": {
    "SourceVersionHash": "fNWTcGIHnnuRL9MgOyJ8nhFzlAU=",
    "VersionHash": "hQP3kd+OaBD0qztZYeM3xQ8YHCs="
  },
  "169,157": {
    "SourceVersionHash": "fNWTcGIHnnuRL9MgOyJ8nhFzlAU=",
    "VersionHash": "hQP3kd+OaBD0qztZYeM3xQ8YHCs="
  },
  "169,158": {
    "SourceVersionHash": "fNWTcGIHnnuRL9MgOyJ8nhFzlAU=",
    "VersionHash": "ucJotee+D6/pLrWwJ8LWlTDp46Q="
  },
  "169,150": {
    "SourceVersionHash": "b7yak2b7t765Rk3g6rky45z0b+c=",
    "VersionHash": "Mu4TKEd9v1ohl3Gv3JDSfuTFE7M="
  }
}