{
  "67,49": {
    "SourceVersionHash": "EsUN4jF1ieeRkEDUqX+YEk0tkiQ=",
    "VersionHash": "6uRXf44MY1ph0ZpNnDnLetTCtBI="
  },
  "68,49": {
    "SourceVersionHash": "jYXueWdma1DhBlpqBGy1OtJEOKc=",
    "VersionHash": "6uRXf44MY1ph0ZpNnDnLetTCtBI="
  },
  "66,49": {
    "SourceVersionHash": "EsUN4jF1ieeRkEDUqX+YEk0tkiQ=",
    "VersionHash": "tn8atJD2opJKvV3X6AEoHChMWSY="
  },
  "65,49": {
    "SourceVersionHash": "uyjtuO1yS4xCvvPgrmDokzMETdc=",
    "VersionHash": "tn8atJD2opJKvV3X6AEoHChMWSY="
  },
  "60,47": {
    "SourceVersionHash": "LYeJWCyW0PdD8zwsmiM3iFJi4rw=",
    "VersionHash": "iaAIpv+hz/25vI9GoZPvCDuNk8Q="
  },
  "60,46": {
    "SourceVersionHash": "LYeJWCyW0PdD8zwsmiM3iFJi4rw=",
    "VersionHash": "lspKOqpJVuUKv0iawrFDDDdvQ4E="
  },
  "60,45": {
    "SourceVersionHash": "RD2ozmqUK4PYYO2kTkmI8+cudV4=",
    "VersionHash": "lspKOqpJVuUKv0iawrFDDDdvQ4E="
  },
  "61,47": {
    "SourceVersionHash": "LYeJWCyW0PdD8zwsmiM3iFJi4rw=",
    "VersionHash": "lspKOqpJVuUKv0iawrFDDDdvQ4E="
  },
  "62,48": {
    "SourceVersionHash": "jNEK+mu04kYwZ4qsSozhyFT/cQo=",
    "VersionHash": "lspKOqpJVuUKv0iawrFDDDdvQ4E="
  },
  "62,47": {
    "SourceVersionHash": "IBkcWSULSnhLsBzd/DHD+alrpuc=",
    "VersionHash": "lspKOqpJVuUKv0iawrFDDDdvQ4E="
  },
  "62,46": {
    "SourceVersionHash": "IBkcWSULSnhLsBzd/DHD+alrpuc=",
    "VersionHash": "On64SXqfWMymzesNRSVdbgsnFqw="
  },
  "61,46": {
    "SourceVersionHash": "LYeJWCyW0PdD8zwsmiM3iFJi4rw=",
    "VersionHash": "On64SXqfWMymzesNRSVdbgsnFqw="
  },
  "62,45": {
    "SourceVersionHash": "bxwia0XoS2S04YniaDM+c/yVEWQ=",
    "VersionHash": "On64SXqfWMymzesNRSVdbgsnFqw="
  },
  "61,45": {
    "SourceVersionHash": "RD2ozmqUK4PYYO2kTkmI8+cudV4=",
    "VersionHash": "On64SXqfWMymzesNRSVdbgsnFqw="
  },
  "60,40": {
    "SourceVersionHash": "9K9FoNGvRxUigweDZe8xYBZ8/PI=",
    "VersionHash": "GiqhwKSRYtBuhCNGA7YdT9YX8nk="
  },
  "62,40": {
    "SourceVersionHash": "laUtvdVl/XFq+fcB1y3RrSm5g8s=",
    "VersionHash": "GiqhwKSRYtBuhCNGA7YdT9YX8nk="
  },
  "61,40": {
    "SourceVersionHash": "9K9FoNGvRxUigweDZe8xYBZ8/PI=",
    "VersionHash": "GiqhwKSRYtBuhCNGA7YdT9YX8nk="
  },
  "64,40": {
    "SourceVersionHash": "kRnQPNqc/MDBvqFHwr1CcOxCOJU=",
    "VersionHash": "ajJl8KlaWvZO/W8lAhs3zYiJqUw="
  },
  "63,40": {
    "SourceVersionHash": "laUtvdVl/XFq+fcB1y3RrSm5g8s=",
    "VersionHash": "ajJl8KlaWvZO/W8lAhs3zYiJqUw="
  },
  "64,41": {
    "SourceVersionHash": "kRnQPNqc/MDBvqFHwr1CcOxCOJU=",
    "VersionHash": "mM6dsFoVcSrxr/h/NrsmBssN/DY="
  },
  "64,42": {
    "SourceVersionHash": "UlLtzNeqK3+NoNKmorBpNQnzRd0=",
    "VersionHash": "mM6dsFoVcSrxr/h/NrsmBssN/DY="
  },
  "63,42": {
    "SourceVersionHash": "XOSDi0w09U5rsPT4668KumU9wcs=",
    "VersionHash": "mM6dsFoVcSrxr/h/NrsmBssN/DY="
  },
  "63,41": {
    "SourceVersionHash": "laUtvdVl/XFq+fcB1y3RrSm5g8s=",
    "VersionHash": "mM6dsFoVcSrxr/h/NrsmBssN/DY="
  },
  "61,41": {
    "SourceVersionHash": "9K9FoNGvRxUigweDZe8xYBZ8/PI=",
    "VersionHash": "mM6dsFoVcSrxr/h/NrsmBssN/DY="
  },
  "62,41": {
    "SourceVersionHash": "laUtvdVl/XFq+fcB1y3RrSm5g8s=",
    "VersionHash": "mM6dsFoVcSrxr/h/NrsmBssN/DY="
  },
  "62,42": {
    "SourceVersionHash": "XOSDi0w09U5rsPT4668KumU9wcs=",
    "VersionHash": "mM6dsFoVcSrxr/h/NrsmBssN/DY="
  },
  "61,42": {
    "SourceVersionHash": "n1QgZlfzv0xb59GpMsNhrHZRcxs=",
    "VersionHash": "mM6dsFoVcSrxr/h/NrsmBssN/DY="
  },
  "63,49": {
    "SourceVersionHash": "jNEK+mu04kYwZ4qsSozhyFT/cQo=",
    "VersionHash": "8I5aOj4IUgSrQGnxVoCvGJi7uzU="
  },
  "64,49": {
    "SourceVersionHash": "uyjtuO1yS4xCvvPgrmDokzMETdc=",
    "VersionHash": "8I5aOj4IUgSrQGnxVoCvGJi7uzU="
  },
  "64,47": {
    "SourceVersionHash": "gab/lsm099f+nWz9ur4y4PkHJAc=",
    "VersionHash": "HFRNOPKY6PuvjJsQ9IvEq5eMESA="
  },
  "64,48": {
    "SourceVersionHash": "uyjtuO1yS4xCvvPgrmDokzMETdc=",
    "VersionHash": "HFRNOPKY6PuvjJsQ9IvEq5eMESA="
  },
  "63,48": {
    "SourceVersionHash": "jNEK+mu04kYwZ4qsSozhyFT/cQo=",
    "VersionHash": "HFRNOPKY6PuvjJsQ9IvEq5eMESA="
  },
  "63,47": {
    "SourceVersionHash": "IBkcWSULSnhLsBzd/DHD+alrpuc=",
    "VersionHash": "HFRNOPKY6PuvjJsQ9IvEq5eMESA="
  },
  "65,47": {
    "SourceVersionHash": "gab/lsm099f+nWz9ur4y4PkHJAc=",
    "VersionHash": "Vl3wAla9+/ZqJgoZGsgUvnuWklM="
  },
  "66,47": {
    "SourceVersionHash": "+5WMMp+NzA4FF7FYKIZbSBiq5Yw=",
    "VersionHash": "Vl3wAla9+/ZqJgoZGsgUvnuWklM="
  },
  "65,48": {
    "SourceVersionHash": "uyjtuO1yS4xCvvPgrmDokzMETdc=",
    "VersionHash": "Vl3wAla9+/ZqJgoZGsgUvnuWklM="
  },
  "66,48": {
    "SourceVersionHash": "EsUN4jF1ieeRkEDUqX+YEk0tkiQ=",
    "VersionHash": "Vl3wAla9+/ZqJgoZGsgUvnuWklM="
  },
  "64,43": {
    "SourceVersionHash": "UlLtzNeqK3+NoNKmorBpNQnzRd0=",
    "VersionHash": "5/1IXWINwMkybpUnH7CeuwGDTe0="
  },
  "63,44": {
    "SourceVersionHash": "bxwia0XoS2S04YniaDM+c/yVEWQ=",
    "VersionHash": "5/1IXWINwMkybpUnH7CeuwGDTe0="
  },
  "63,43": {
    "SourceVersionHash": "XOSDi0w09U5rsPT4668KumU9wcs=",
    "VersionHash": "5/1IXWINwMkybpUnH7CeuwGDTe0="
  },
  "64,44": {
    "SourceVersionHash": "d4o0/6J+Kp1a8RSuqcXPzeziLeQ=",
    "VersionHash": "5/1IXWINwMkybpUnH7CeuwGDTe0="
  },
  "62,43": {
    "SourceVersionHash": "XOSDi0w09U5rsPT4668KumU9wcs=",
    "VersionHash": "5/1IXWINwMkybpUnH7CeuwGDTe0="
  },
  "61,43": {
    "SourceVersionHash": "n1QgZlfzv0xb59GpMsNhrHZRcxs=",
    "VersionHash": "5/1IXWINwMkybpUnH7CeuwGDTe0="
  },
  "61,44": {
    "SourceVersionHash": "RD2ozmqUK4PYYO2kTkmI8+cudV4=",
    "VersionHash": "5/1IXWINwMkybpUnH7CeuwGDTe0="
  },
  "62,44": {
    "SourceVersionHash": "bxwia0XoS2S04YniaDM+c/yVEWQ=",
    "VersionHash": "5/1IXWINwMkybpUnH7CeuwGDTe0="
  },
  "65,42": {
    "SourceVersionHash": "UlLtzNeqK3+NoNKmorBpNQnzRd0=",
    "VersionHash": "IwdS83hUQWAGc4FbT0E0XzF2PXw="
  },
  "65,40": {
    "SourceVersionHash": "kRnQPNqc/MDBvqFHwr1CcOxCOJU=",
    "VersionHash": "IwdS83hUQWAGc4FbT0E0XzF2PXw="
  },
  "65,41": {
    "SourceVersionHash": "kRnQPNqc/MDBvqFHwr1CcOxCOJU=",
    "VersionHash": "IwdS83hUQWAGc4FbT0E0XzF2PXw="
  },
  "62,49": {
    "SourceVersionHash": "jNEK+mu04kYwZ4qsSozhyFT/cQo=",
    "VersionHash": "tmSn1bs3+138HMNJvqbaR3GSFDI="
  },
  "60,44": {
    "SourceVersionHash": "RD2ozmqUK4PYYO2kTkmI8+cudV4=",
    "VersionHash": "rcWHljTae/Qsg5Zk3Y7Ju2z/82A="
  },
  "60,43": {
    "SourceVersionHash": "n1QgZlfzv0xb59GpMsNhrHZRcxs=",
    "VersionHash": "rcWHljTae/Qsg5Zk3Y7Ju2z/82A="
  },
  "60,42": {
    "SourceVersionHash": "n1QgZlfzv0xb59GpMsNhrHZRcxs=",
    "VersionHash": "rcWHljTae/Qsg5Zk3Y7Ju2z/82A="
  },
  "60,41": {
    "SourceVersionHash": "9K9FoNGvRxUigweDZe8xYBZ8/PI=",
    "VersionHash": "rcWHljTae/Qsg5Zk3Y7Ju2z/82A="
  },
  "68,46": {
    "SourceVersionHash": "uY8ucxAdgfAihlYyOUkN6wQNl+Y=",
    "VersionHash": "tqaHNkDNpqxGxYGUFLwpwEXl220="
  },
  "67,46": {
    "SourceVersionHash": "+5WMMp+NzA4FF7FYKIZbSBiq5Yw=",
    "VersionHash": "tqaHNkDNpqxGxYGUFLwpwEXl220="
  },
  "65,45": {
    "SourceVersionHash": "d4o0/6J+Kp1a8RSuqcXPzeziLeQ=",
    "VersionHash": "tqaHNkDNpqxGxYGUFLwpwEXl220="
  },
  "65,46": {
    "SourceVersionHash": "gab/lsm099f+nWz9ur4y4PkHJAc=",
    "VersionHash": "tqaHNkDNpqxGxYGUFLwpwEXl220="
  },
  "66,46": {
    "SourceVersionHash": "+5WMMp+NzA4FF7FYKIZbSBiq5Yw=",
    "VersionHash": "tqaHNkDNpqxGxYGUFLwpwEXl220="
  },
  "68,47": {
    "SourceVersionHash": "uY8ucxAdgfAihlYyOUkN6wQNl+Y=",
    "VersionHash": "tqaHNkDNpqxGxYGUFLwpwEXl220="
  },
  "67,47": {
    "SourceVersionHash": "+5WMMp+NzA4FF7FYKIZbSBiq5Yw=",
    "VersionHash": "tqaHNkDNpqxGxYGUFLwpwEXl220="
  },
  "68,48": {
    "SourceVersionHash": "jYXueWdma1DhBlpqBGy1OtJEOKc=",
    "VersionHash": "tqaHNkDNpqxGxYGUFLwpwEXl220="
  },
  "67,48": {
    "SourceVersionHash": "EsUN4jF1ieeRkEDUqX+YEk0tkiQ=",
    "VersionHash": "tqaHNkDNpqxGxYGUFLwpwEXl220="
  },
  "69,46": {
    "SourceVersionHash": "uY8ucxAdgfAihlYyOUkN6wQNl+Y=",
    "VersionHash": "S/jaKG6AI25APj5bQGI3QOyHi6k="
  },
  "69,47": {
    "SourceVersionHash": "uY8ucxAdgfAihlYyOUkN6wQNl+Y=",
    "VersionHash": "J+aqijGSaX/KVBnQ/k6FiICTGHQ="
  },
  "69,48": {
    "SourceVersionHash": "jYXueWdma1DhBlpqBGy1OtJEOKc=",
    "VersionHash": "J+aqijGSaX/KVBnQ/k6FiICTGHQ="
  },
  "65,44": {
    "SourceVersionHash": "d4o0/6J+Kp1a8RSuqcXPzeziLeQ=",
    "VersionHash": "J+aqijGSaX/KVBnQ/k6FiICTGHQ="
  },
  "65,43": {
    "SourceVersionHash": "UlLtzNeqK3+NoNKmorBpNQnzRd0=",
    "VersionHash": "J+aqijGSaX/KVBnQ/k6FiICTGHQ="
  },
  "64,46": {
    "SourceVersionHash": "gab/lsm099f+nWz9ur4y4PkHJAc=",
    "VersionHash": "q9psJ2m1S8TNopjl+R7XO5OcvKk="
  },
  "63,45": {
    "SourceVersionHash": "bxwia0XoS2S04YniaDM+c/yVEWQ=",
    "VersionHash": "q9psJ2m1S8TNopjl+R7XO5OcvKk="
  },
  "64,45": {
    "SourceVersionHash": "d4o0/6J+Kp1a8RSuqcXPzeziLeQ=",
    "VersionHash": "q9psJ2m1S8TNopjl+R7XO5OcvKk="
  },
  "63,46": {
    "SourceVersionHash": "IBkcWSULSnhLsBzd/DHD+alrpuc=",
    "VersionHash": "q9psJ2m1S8TNopjl+R7XO5OcvKk="
  },
  "69,49": {
    "SourceVersionHash": "jYXueWdma1DhBlpqBGy1OtJEOKc=",
    "VersionHash": "pmOeK/yp3cs80szPrI/DZIxA90U="
  }
}