{
  "169,99": {
    "SourceVersionHash": "yG2+CGbn7Hda/Rkj27tM6rNdG3g=",
    "VersionHash": "Dc3eIJ42EjzvXs5bx4xOw2qFL18="
  },
  "168,99": {
    "SourceVersionHash": "yG2+CGbn7Hda/Rkj27tM6rNdG3g=",
    "VersionHash": "Dc3eIJ42EjzvXs5bx4xOw2qFL18="
  },
  "169,97": {
    "SourceVersionHash": "yG2+CGbn7Hda/Rkj27tM6rNdG3g=",
    "VersionHash": "26BH4PBkqj/D4NcENLTgk4U8P4I="
  },
  "169,98": {
    "SourceVersionHash": "yG2+CGbn7Hda/Rkj27tM6rNdG3g=",
    "VersionHash": "26BH4PBkqj/D4NcENLTgk4U8P4I="
  },
  "168,97": {
    "SourceVersionHash": "yG2+CGbn7Hda/Rkj27tM6rNdG3g=",
    "VersionHash": "26BH4PBkqj/D4NcENLTgk4U8P4I="
  },
  "168,98": {
    "SourceVersionHash": "yG2+CGbn7Hda/Rkj27tM6rNdG3g=",
    "VersionHash": "26BH4PBkqj/D4NcENLTgk4U8P4I="
  },
  "169,96": {
    "SourceVersionHash": "yG2+CGbn7Hda/Rkj27tM6rNdG3g=",
    "VersionHash": "26BH4PBkqj/D4NcENLTgk4U8P4I="
  },
  "168,96": {
    "SourceVersionHash": "yG2+CGbn7Hda/Rkj27tM6rNdG3g=",
    "VersionHash": "26BH4PBkqj/D4NcENLTgk4U8P4I="
  },
  "162,93": {
    "SourceVersionHash": "0ePCzv0+/vH2QVw3FG9dWjBl+bM=",
    "VersionHash": "ix241bfHgitzYKrV/BiVlW0JTjk="
  },
  "162,94": {
    "SourceVersionHash": "0ePCzv0+/vH2QVw3FG9dWjBl+bM=",
    "VersionHash": "ix241bfHgitzYKrV/BiVlW0JTjk="
  },
  "160,93": {
    "SourceVersionHash": "0ePCzv0+/vH2QVw3FG9dWjBl+bM=",
    "VersionHash": "ix241bfHgitzYKrV/BiVlW0JTjk="
  },
  "161,93": {
    "SourceVersionHash": "0ePCzv0+/vH2QVw3FG9dWjBl+bM=",
    "VersionHash": "ix241bfHgitzYKrV/BiVlW0JTjk="
  },
  "161,94": {
    "SourceVersionHash": "0ePCzv0+/vH2QVw3FG9dWjBl+bM=",
    "VersionHash": "ix241bfHgitzYKrV/BiVlW0JTjk="
  },
  "160,94": {
    "SourceVersionHash": "0ePCzv0+/vH2QVw3FG9dWjBl+bM=",
    "VersionHash": "ix241bfHgitzYKrV/BiVlW0JTjk="
  },
  "160,92": {
    "SourceVersionHash": "0ePCzv0+/vH2QVw3FG9dWjBl+bM=",
    "VersionHash": "ix241bfHgitzYKrV/BiVlW0JTjk="
  },
  "162,95": {
    "SourceVersionHash": "0ePCzv0+/vH2QVw3FG9dWjBl+bM=",
    "VersionHash": "ix241bfHgitzYKrV/BiVlW0JTjk="
  },
  "161,92": {
    "SourceVersionHash": "0ePCzv0+/vH2QVw3FG9dWjBl+bM=",
    "VersionHash": "ix241bfHgitzYKrV/BiVlW0JTjk="
  },
  "162,92": {
    "SourceVersionHash": "0ePCzv0+/vH2QVw3FG9dWjBl+bM=",
    "VersionHash": "ix241bfHgitzYKrV/BiVlW0JTjk="
  },
  "161,95": {
    "SourceVersionHash": "0ePCzv0+/vH2QVw3FG9dWjBl+bM=",
    "VersionHash": "ix241bfHgitzYKrV/BiVlW0JTjk="
  },
  "163,92": {
    "SourceVersionHash": "0ePCzv0+/vH2QVw3FG9dWjBl+bM=",
    "VersionHash": "ix241bfHgitzYKrV/BiVlW0JTjk="
  },
  "163,93": {
    "SourceVersionHash": "0ePCzv0+/vH2QVw3FG9dWjBl+bM=",
    "VersionHash": "ix241bfHgitzYKrV/BiVlW0JTjk="
  },
  "163,94": {
    "SourceVersionHash": "0ePCzv0+/vH2QVw3FG9dWjBl+bM=",
    "VersionHash": "ix241bfHgitzYKrV/BiVlW0JTjk="
  },
  "160,95": {
    "SourceVersionHash": "0ePCzv0+/vH2QVw3FG9dWjBl+bM=",
    "VersionHash": "ix241bfHgitzYKrV/BiVlW0JTjk="
  },
  "163,95": {
    "SourceVersionHash": "0ePCzv0+/vH2QVw3FG9dWjBl+bM=",
    "VersionHash": "ix241bfHgitzYKrV/BiVlW0JTjk="
  }
}